prompt_amplifier/__init__.py
prompt_amplifier/cli.py
prompt_amplifier/version.py
prompt_amplifier/cache/__init__.py
prompt_amplifier/cache/base.py
prompt_amplifier/cache/disk.py
prompt_amplifier/cache/memory.py
prompt_amplifier/chunkers/__init__.py
prompt_amplifier/chunkers/base.py
prompt_amplifier/chunkers/recursive.py
prompt_amplifier/core/__init__.py
prompt_amplifier/core/config.py
prompt_amplifier/core/engine.py
prompt_amplifier/core/exceptions.py
prompt_amplifier/embedders/__init__.py
prompt_amplifier/embedders/base.py
prompt_amplifier/embedders/cohere.py
prompt_amplifier/embedders/google.py
prompt_amplifier/embedders/openai.py
prompt_amplifier/embedders/sentence_transformers.py
prompt_amplifier/embedders/tfidf.py
prompt_amplifier/embedders/voyage.py
prompt_amplifier/evaluation/__init__.py
prompt_amplifier/evaluation/metrics.py
prompt_amplifier/generators/__init__.py
prompt_amplifier/generators/anthropic.py
prompt_amplifier/generators/base.py
prompt_amplifier/generators/google.py
prompt_amplifier/generators/ollama.py
prompt_amplifier/generators/openai.py
prompt_amplifier/loaders/__init__.py
prompt_amplifier/loaders/base.py
prompt_amplifier/loaders/csv.py
prompt_amplifier/loaders/docx.py
prompt_amplifier/loaders/excel.py
prompt_amplifier/loaders/json.py
prompt_amplifier/loaders/pdf.py
prompt_amplifier/loaders/txt.py
prompt_amplifier/loaders/web.py
prompt_amplifier/models/__init__.py
prompt_amplifier/models/document.py
prompt_amplifier/models/embedding.py
prompt_amplifier/models/result.py
prompt_amplifier/retrievers/__init__.py
prompt_amplifier/retrievers/base.py
prompt_amplifier/retrievers/hybrid.py
prompt_amplifier/retrievers/vector.py
prompt_amplifier/vectorstores/__init__.py
prompt_amplifier/vectorstores/base.py
prompt_amplifier/vectorstores/chroma.py
prompt_amplifier/vectorstores/faiss.py
prompt_amplifier/vectorstores/memory.py
prompt_amplifier-0.2.2.dist-info/licenses/LICENSE
prompt_amplifier-0.2.2.dist-info/METADATA
prompt_amplifier-0.2.2.dist-info/WHEEL
prompt_amplifier-0.2.2.dist-info/entry_points.txt
prompt_amplifier-0.2.2.dist-info/top_level.txt
prompt_amplifier-0.2.2.dist-info/RECORD
