Metadata-Version: 2.4
Name: prompt-amplifier
Version: 0.2.2
Summary: Transform short prompts into detailed, structured instructions using context-aware retrieval
Author-email: Rajesh More <moreyrb@gmail.com>
License: Apache-2.0
Project-URL: Homepage, https://github.com/DeccanX/Prompt-Amplifier
Project-URL: Documentation, https://prompt-amplifier.readthedocs.io
Project-URL: Repository, https://github.com/DeccanX/Prompt-Amplifier
Project-URL: Issues, https://github.com/DeccanX/Prompt-Amplifier/issues
Keywords: prompt-engineering,llm,rag,retrieval-augmented-generation,prompt-expansion,ai,nlp,vector-search,embeddings
Classifier: Development Status :: 3 - Alpha
Classifier: Intended Audience :: Developers
Classifier: Intended Audience :: Science/Research
Classifier: License :: OSI Approved :: Apache Software License
Classifier: Operating System :: OS Independent
Classifier: Programming Language :: Python :: 3
Classifier: Programming Language :: Python :: 3.9
Classifier: Programming Language :: Python :: 3.10
Classifier: Programming Language :: Python :: 3.11
Classifier: Programming Language :: Python :: 3.12
Classifier: Topic :: Scientific/Engineering :: Artificial Intelligence
Classifier: Topic :: Text Processing :: Linguistic
Requires-Python: >=3.9
License-File: LICENSE
Requires-Dist: numpy>=1.24.0
Requires-Dist: scikit-learn>=1.3.0
Requires-Dist: pydantic>=2.0.0
Requires-Dist: typing-extensions>=4.0.0
Provides-Extra: loaders
Requires-Dist: python-docx>=0.8.11; extra == "loaders"
Requires-Dist: openpyxl>=3.0.0; extra == "loaders"
Requires-Dist: pandas>=1.3.0; extra == "loaders"
Requires-Dist: pymupdf>=1.23.0; extra == "loaders"
Requires-Dist: beautifulsoup4>=4.9.0; extra == "loaders"
Requires-Dist: markdown>=3.3.0; extra == "loaders"
Provides-Extra: loaders-web
Requires-Dist: requests>=2.28.0; extra == "loaders-web"
Requires-Dist: beautifulsoup4>=4.9.0; extra == "loaders-web"
Requires-Dist: lxml>=4.9.0; extra == "loaders-web"
Provides-Extra: loaders-youtube
Requires-Dist: youtube-transcript-api>=0.6.0; extra == "loaders-youtube"
Provides-Extra: loaders-rss
Requires-Dist: feedparser>=6.0.0; extra == "loaders-rss"
Provides-Extra: embeddings-local
Requires-Dist: sentence-transformers>=2.2.0; extra == "embeddings-local"
Requires-Dist: fastembed>=0.1.0; extra == "embeddings-local"
Provides-Extra: embeddings-openai
Requires-Dist: openai>=1.0.0; extra == "embeddings-openai"
Provides-Extra: embeddings-cohere
Requires-Dist: cohere>=5.0.0; extra == "embeddings-cohere"
Provides-Extra: embeddings-voyage
Requires-Dist: voyageai>=0.2.0; extra == "embeddings-voyage"
Provides-Extra: embeddings-jina
Requires-Dist: requests>=2.28.0; extra == "embeddings-jina"
Provides-Extra: embeddings-mistral
Requires-Dist: mistralai>=0.1.0; extra == "embeddings-mistral"
Provides-Extra: embeddings-google
Requires-Dist: google-generativeai>=0.3.0; extra == "embeddings-google"
Provides-Extra: vectorstore-chroma
Requires-Dist: chromadb>=0.4.0; extra == "vectorstore-chroma"
Provides-Extra: vectorstore-faiss
Requires-Dist: faiss-cpu>=1.7.0; extra == "vectorstore-faiss"
Provides-Extra: vectorstore-lancedb
Requires-Dist: lancedb>=0.1.0; extra == "vectorstore-lancedb"
Provides-Extra: vectorstore-qdrant
Requires-Dist: qdrant-client>=1.6.0; extra == "vectorstore-qdrant"
Provides-Extra: vectorstore-pinecone
Requires-Dist: pinecone-client>=2.0.0; extra == "vectorstore-pinecone"
Provides-Extra: vectorstore-weaviate
Requires-Dist: weaviate-client>=3.0.0; extra == "vectorstore-weaviate"
Provides-Extra: generators-openai
Requires-Dist: openai>=1.0.0; extra == "generators-openai"
Provides-Extra: generators-anthropic
Requires-Dist: anthropic>=0.18.0; extra == "generators-anthropic"
Provides-Extra: generators-google
Requires-Dist: google-generativeai>=0.3.0; extra == "generators-google"
Provides-Extra: generators-ollama
Requires-Dist: ollama>=0.1.0; extra == "generators-ollama"
Provides-Extra: generators-mistral
Requires-Dist: mistralai>=0.1.0; extra == "generators-mistral"
Provides-Extra: generators-together
Requires-Dist: requests>=2.28.0; extra == "generators-together"
Provides-Extra: dev
Requires-Dist: pytest>=7.0.0; extra == "dev"
Requires-Dist: pytest-cov>=4.0.0; extra == "dev"
Requires-Dist: pytest-asyncio>=0.21.0; extra == "dev"
Requires-Dist: black>=23.0.0; extra == "dev"
Requires-Dist: ruff>=0.1.0; extra == "dev"
Requires-Dist: mypy>=1.0.0; extra == "dev"
Requires-Dist: pre-commit>=3.0.0; extra == "dev"
Provides-Extra: docs
Requires-Dist: mkdocs>=1.5.0; extra == "docs"
Requires-Dist: mkdocs-material>=9.0.0; extra == "docs"
Requires-Dist: mkdocstrings[python]>=0.24.0; extra == "docs"
Provides-Extra: all
Requires-Dist: prompt-amplifier[loaders]; extra == "all"
Requires-Dist: prompt-amplifier[embeddings-local]; extra == "all"
Requires-Dist: prompt-amplifier[embeddings-openai]; extra == "all"
Requires-Dist: prompt-amplifier[vectorstore-chroma]; extra == "all"
Requires-Dist: prompt-amplifier[vectorstore-faiss]; extra == "all"
Requires-Dist: prompt-amplifier[generators-openai]; extra == "all"
Requires-Dist: prompt-amplifier[generators-anthropic]; extra == "all"
Requires-Dist: prompt-amplifier[generators-google]; extra == "all"
Dynamic: license-file
